kadota/__init__.py
kadota/figmatools.py
kadota/utils.py
kadota-1.1.0.dist-info/LICENSE
kadota-1.1.0.dist-info/METADATA
kadota-1.1.0.dist-info/WHEEL
kadota-1.1.0.dist-info/top_level.txt
kadota-1.1.0.dist-info/RECORD
