Metadata-Version: 2.1
Name: kadota
Version: 1.1.0
Summary: Tools for working with Figma programmatically
Author: Isaac Ronald Ward
Author-email: isaacronaldward@gmail.com
License: MIT
License-File: LICENSE
Requires-Dist: requests (==2.28.1)
Requires-Dist: setuptools (==65.6.3)
